<?xml version="1.0" encoding="UTF-8"?>
<odoo>
    <data>
        <record id="resource_calendar_inherit_form" model="ir.ui.view">
            <field name="name">resource.calendar.inherit.form</field>
            <field name="model">resource.calendar</field>
            <field name="inherit_id" ref="resource.resource_calendar_form"/>
            <field name="arch" type="xml">
                <xpath expr="//sheet/div[@name='button_box']" position="inside">
                    <button name="toggle_active" type="object" class="oe_stat_button" icon="fa-archive">
                        <field name="active" widget="boolean_button" options="{'terminology': 'active'}" modifiers="{}"/>
                    </button>
                </xpath>
                <xpath expr="//field[@name='hours_per_day']" position="replace">
                    <field name="hours_per_day" widget="float_time"/>
                    <field name="start_hour" widget="float_time"/>
                    <field name="finish_hour" widget="float_time"/>
                    <field name="starting_day"/>
                    <field name="finish_day"/>
                    <field name="break_time" widget="float_time"/>
                </xpath>
            </field>
        </record>
    </data>
</odoo>