<?xml version="1.0"?>
<odoo>
    <!--record model="ir.ui.view" id="view_account_reg_payment_form_inh_l10n_mx">
        <field name="name">view.account.reg.payment.form.inh.l10n.mx</field>
        <field name="model">account.register.payments</field>
        <field name="inherit_id" ref="account.view_account_payment_from_invoices"/>
        <field name="arch" type="xml">
            <data>
                <xpath expr="//field[@name='journal_id']" position="after">
                    <field name="cfdi" attrs="{'invisible': [('payment_type', '!=', 'outbound')]}"/>
                </xpath>
            </data>
        </field>
    </record-->
</odoo>
